fujin/__init__.py
fujin/__main__.py
fujin/_installer.py
fujin/audit.py
fujin/caddy.py
fujin/config.py
fujin/connection.py
fujin/discovery.py
fujin/errors.py
fujin/fa.py
fujin/formatting.py
fujin/secrets.py
fujin/templates.py
fujin/commands/__init__.py
fujin/commands/_base.py
fujin/commands/app.py
fujin/commands/audit.py
fujin/commands/deploy.py
fujin/commands/down.py
fujin/commands/init.py
fujin/commands/migrate.py
fujin/commands/new.py
fujin/commands/prune.py
fujin/commands/rollback.py
fujin/commands/server.py
fujin/commands/showenv.py
fujin/commands/up.py
fujin_cli-0.20.4.dist-info/METADATA
fujin_cli-0.20.4.dist-info/WHEEL
fujin_cli-0.20.4.dist-info/entry_points.txt
fujin_cli-0.20.4.dist-info/licenses/LICENSE.txt
fujin_cli-0.20.4.dist-info/RECORD
