Metadata-Version: 2.4
Name: fujin-cli
Version: 0.20.4
Summary: Get your project up and running in a few minutes on your own vps.
Project-URL: Documentation, https://github.com/Tobi-De/fujin#readme
Project-URL: Issues, https://github.com/Tobi-De/fujin/issues
Project-URL: Source, https://github.com/Tobi-De/fujin
Author-email: Tobi DEGNON <tobidegnon@proton.me>
License-File: LICENSE.txt
Keywords: caddy,deployment,django,fastapi,litestar,python,systemd
Classifier: Development Status :: 3 - Alpha
Classifier: Intended Audience :: Developers
Classifier: Natural Language :: English
Classifier: Programming Language :: Python
Classifier: Programming Language :: Python :: 3 :: Only
Classifier: Programming Language :: Python :: 3.10
Classifier: Programming Language :: Python :: 3.11
Classifier: Programming Language :: Python :: 3.12
Classifier: Programming Language :: Python :: 3.13
Classifier: Programming Language :: Python :: 3.14
Classifier: Programming Language :: Python :: Implementation :: CPython
Classifier: Programming Language :: Python :: Implementation :: PyPy
Requires-Python: >=3.10
Requires-Dist: cappa>=0.31
Requires-Dist: msgspec[toml]>=0.20
Requires-Dist: python-dotenv>=1.2.1
Requires-Dist: rich>=14.3.1
Requires-Dist: ssh2-python>=1.2.0.post1
